covid_seird/__init__.py
covid_seird/country_covid_seird.py
covid_seird/exceptions.py
covid_seird-0.0.8.dist-info/LICENSE
covid_seird-0.0.8.dist-info/METADATA
covid_seird-0.0.8.dist-info/WHEEL
covid_seird-0.0.8.dist-info/top_level.txt
covid_seird-0.0.8.dist-info/RECORD
