Metadata-Version: 2.1
Name: covid-seird
Version: 0.0.8
Summary: A small package that implements the SEIRD Epidemiological                    Model on COVID-19 data.
Home-page: https://github.com/paulorobertobranco/covid_seird
Author: Paulo Branco
Author-email: paulorobertobranco@gmail.com
License: UNKNOWN
Platform: UNKNOWN
Classifier: Programming Language :: Python :: 3
Classifier: License :: OSI Approved :: MIT License
Classifier: Operating System :: OS Independent
Requires-Python: >=3.6
Requires-Dist: numpy
Requires-Dist: pandas
Requires-Dist: lmfit
Requires-Dist: requests
Requires-Dist: COVID19Py
Requires-Dist: scipy
Requires-Dist: matplotlib
